pyrpc_schedule/__init__.py
pyrpc_schedule/databases/__init__.py
pyrpc_schedule/databases/client/__init__.py
pyrpc_schedule/databases/client/client.py
pyrpc_schedule/databases/databases/__init__.py
pyrpc_schedule/databases/databases/databases.py
pyrpc_schedule/main/__init__.py
pyrpc_schedule/main/run.py
pyrpc_schedule/main/server/__init__.py
pyrpc_schedule/main/server/run_service.py
pyrpc_schedule/main/worker/__init__.py
pyrpc_schedule/main/worker/run_worker.py
pyrpc_schedule/meta/__init__.py
pyrpc_schedule/meta/abcmeta.py
pyrpc_schedule/meta/key.py
pyrpc_schedule/rabbit/__init__.py
pyrpc_schedule/rabbit/message/__init__.py
pyrpc_schedule/rabbit/message/message.py
pyrpc_schedule/rabbit/rabbit/__init__.py
pyrpc_schedule/rabbit/rabbit/rabbit.py
pyrpc_schedule/rabbit/rpc_proxy/__init__.py
pyrpc_schedule/rabbit/rpc_proxy/rpc_proxy.py
pyrpc_schedule/services/__init__.py
pyrpc_schedule/services/monitoring/__init__.py
pyrpc_schedule/services/monitoring/heartbeat_detection.py
pyrpc_schedule/services/monitoring/system_info.py
pyrpc_schedule/services/schedule/__init__.py
pyrpc_schedule/services/schedule/run_schedule.py
pyrpc_schedule/services/schedule/task_distribution.py
pyrpc_schedule/services/web/__init__.py
pyrpc_schedule/services/web/run_http_server.py
pyrpc_schedule/utils/__init__.py
pyrpc_schedule/utils/cipher/__init__.py
pyrpc_schedule/utils/cipher/cipher.py
pyrpc_schedule/utils/format_time/__init__.py
pyrpc_schedule/utils/format_time/format_time.py
pyrpc_schedule/utils/generate_id/__init__.py
pyrpc_schedule/utils/generate_id/generate_id.py
pyrpc_schedule/utils/logger/__init__.py
pyrpc_schedule/utils/logger/logger.py
pyrpc_schedule/utils/network/__init__.py
pyrpc_schedule/utils/network/socket_tools.py
PyrpcSchedule-1.2.3.dist-info/METADATA
PyrpcSchedule-1.2.3.dist-info/WHEEL
PyrpcSchedule-1.2.3.dist-info/top_level.txt
PyrpcSchedule-1.2.3.dist-info/RECORD
