Metadata-Version: 2.2
Name: PyrpcSchedule
Version: 1.2.3
Summary: PyrpcSchedule Description
Home-page: https://gitee.com/ZYPH/pyrpc-schedule
Author: YanPing
Author-email: zyphhxx@foxmail.com
Maintainer: YanPing
Maintainer-email: zyphhxx@foxmail.com
License: MIT License
Classifier: Development Status :: 3 - Alpha
Classifier: Intended Audience :: Developers
Classifier: Topic :: Software Development :: Build Tools
Classifier: License :: OSI Approved :: MIT License
Classifier: Programming Language :: Python :: 3
Requires-Python: >=3.8
Requires-Dist: amqp~=5.0.6
Requires-Dist: eventlet~=0.39.0
Requires-Dist: Jinja2~=3.1.5
Requires-Dist: flask~=3.1.0
Requires-Dist: kombu~=5.2.2
Requires-Dist: kombu~=5.2.2
Requires-Dist: nameko~=2.14.1
Requires-Dist: pika~=1.3.2
Requires-Dist: pytz~=2024.1
Requires-Dist: psutil~=5.9.0
Requires-Dist: pycryptodomex~=3.21.0
Requires-Dist: pymongo~=4.8.0
Dynamic: author
Dynamic: author-email
Dynamic: classifier
Dynamic: description
Dynamic: home-page
Dynamic: license
Dynamic: maintainer
Dynamic: maintainer-email
Dynamic: requires-dist
Dynamic: requires-python
Dynamic: summary
